drf_ebs_utils/__init__.py
drf_ebs_utils/config/__init__.py
drf_ebs_utils/config/settings.py
drf_ebs_utils/helpers/__init__.py
drf_ebs_utils/helpers/attachment.py
drf_ebs_utils/helpers/notification.py
drf_ebs_utils/services/__init__.py
drf_ebs_utils/services/abstract.py
drf_ebs_utils/services/attachment.py
drf_ebs_utils/services/notification.py
drf_ebs_utils/services/sso.py
drf_ebs_utils-0.0.45.dist-info/LICENSE.md
drf_ebs_utils-0.0.45.dist-info/METADATA
drf_ebs_utils-0.0.45.dist-info/WHEEL
drf_ebs_utils-0.0.45.dist-info/top_level.txt
drf_ebs_utils-0.0.45.dist-info/RECORD
