Metadata-Version: 2.1
Name: drf-ebs-utils
Version: 0.0.45
Summary: drf-ebs-utils is a package that offers service classes for notification-service, attachment-service, sso-service.
Home-page: https://github.com/ebs-integrator/drf-ebs-utils
Author: Dorin Musteata
Author-email: dorin.musteata@ebs-integrator.com
License: UNKNOWN
Project-URL: Bug Tracker, https://github.com/ebs-integrator/drf-ebs-utils/issues
Platform: UNKNOWN
Classifier: Programming Language :: Python :: 3
Classifier: Programming Language :: Python :: 3.6
Classifier: Programming Language :: Python :: 3.7
Classifier: Programming Language :: Python :: 3.8
Classifier: Programming Language :: Python :: 3.9
Classifier: License :: OSI Approved :: MIT License
Classifier: Operating System :: OS Independent
Requires-Python: >=3.8
License-File: LICENSE.md
